fsqc/__init__.py
fsqc/checkCCSize.py
fsqc/checkContrast.py
fsqc/checkRotation.py
fsqc/checkSNR.py
fsqc/checkTopology.py
fsqc/createScreenshots.py
fsqc/createSurfacePlots.py
fsqc/evaluateFornixSegmentation.py
fsqc/evaluateHippocampalSegmentation.py
fsqc/evaluateHypothalamicSegmentation.py
fsqc/fsqcMain.py
fsqc/fsqcUtils.py
fsqc/outlierDetection.py
fsqc/cli/__init__.py
fsqc/commands/__init__.py
fsqc/commands/sys_info.py
fsqc/utils/__init__.py
fsqc/utils/_config.py
fsqc/utils/_imports.py
fsqc-2.1.6.dist-info/licenses/LICENSE
fsqc-2.1.6.dist-info/METADATA
fsqc-2.1.6.dist-info/WHEEL
fsqc-2.1.6.dist-info/entry_points.txt
fsqc-2.1.6.dist-info/top_level.txt
fsqc-2.1.6.dist-info/RECORD
