Metadata-Version: 2.4
Name: fsqc
Version: 2.1.6
Summary: Quality control scripts for FastSurfer and FreeSurfer structural MRI data
Author-email: Kersten Diers <kersten.diers@dzne.de>, Martin Reuter <martin.reuter@dzne.de>
Maintainer-email: Kersten Diers <kersten.diers@dzne.de>, Martin Reuter <martin.reuter@dzne.de>
License: MIT License
Project-URL: homepage, https://github.com/Deep-MI/fsqc
Project-URL: documentation, https://github.com/Deep-MI/fsqc
Project-URL: source, https://github.com/Deep-MI/fsqc
Project-URL: tracker, https://github.com/Deep-MI/fsqc/issues
Keywords: FastSurfer,FreeSurfer,Quality control,Quality assurance
Classifier: Operating System :: Unix
Classifier: Operating System :: MacOS
Classifier: Programming Language :: Python :: 3 :: Only
Classifier: Programming Language :: Python :: 3.9
Classifier: Programming Language :: Python :: 3.10
Classifier: Programming Language :: Python :: 3.11
Classifier: Programming Language :: Python :: 3.12
Classifier: Natural Language :: English
Classifier: License :: OSI Approved :: MIT License
Classifier: Intended Audience :: Science/Research
Requires-Python: >=3.9
License-File: LICENSE
Requires-Dist: brainprint==0.4.0
Requires-Dist: lapy>=1.1.1
Requires-Dist: matplotlib
Requires-Dist: nibabel
Requires-Dist: numpy
Requires-Dist: pandas
Requires-Dist: scipy
Requires-Dist: scikit-image
Requires-Dist: transforms3d
Requires-Dist: pyopengl
Requires-Dist: glfw
Requires-Dist: pillow
Requires-Dist: pyrr
Requires-Dist: PyQt6
Requires-Dist: whippersnappy>=1.3.0
Provides-Extra: build
Requires-Dist: build; extra == "build"
Requires-Dist: twine; extra == "build"
Provides-Extra: doc
Requires-Dist: furo!=2023.8.17; extra == "doc"
Requires-Dist: matplotlib; extra == "doc"
Requires-Dist: memory-profiler; extra == "doc"
Requires-Dist: numpydoc; extra == "doc"
Requires-Dist: sphinx!=7.2.*; extra == "doc"
Requires-Dist: sphinxcontrib-bibtex; extra == "doc"
Requires-Dist: sphinx-copybutton; extra == "doc"
Requires-Dist: sphinx-design; extra == "doc"
Requires-Dist: sphinx-gallery; extra == "doc"
Requires-Dist: sphinx-issues; extra == "doc"
Requires-Dist: pypandoc; extra == "doc"
Requires-Dist: nbsphinx; extra == "doc"
Requires-Dist: IPython; extra == "doc"
Requires-Dist: ipykernel; extra == "doc"
Provides-Extra: style
Requires-Dist: bibclean; extra == "style"
Requires-Dist: codespell; extra == "style"
Requires-Dist: pydocstyle[toml]; extra == "style"
Requires-Dist: ruff; extra == "style"
Provides-Extra: test
Requires-Dist: pytest; extra == "test"
Requires-Dist: pytest-cov; extra == "test"
Requires-Dist: pytest-timeout; extra == "test"
Provides-Extra: all
Requires-Dist: fsqc[build]; extra == "all"
Requires-Dist: fsqc[doc]; extra == "all"
Requires-Dist: fsqc[style]; extra == "all"
Provides-Extra: full
Requires-Dist: fsqc[all]; extra == "full"
Dynamic: license-file
